{"indices":[{"name":"코스피","symbol":"^KS11","currency":"KRW","price":7475.94,"change":184.03,"changePct":2.52,"marketStatus":"CLOSE"},{"name":"코스닥","symbol":"^KQ11","currency":"KRW","price":837.43,"change":43.43,"changePct":5.47,"marketStatus":"CLOSE"},{"name":"S&P 500","symbol":"^GSPC","currency":"USD","price":7543.64,"change":60.93000000000029,"changePct":0.8142771803263831,"marketStatus":"CLOSE"},{"name":"나스닥","symbol":"^IXIC","currency":"USD","price":26206.89,"change":336.2380000000012,"changePct":1.2996889293706289,"marketStatus":"CLOSE"},{"name":"VIX","symbol":"^VIX","currency":"USD","price":16.06,"change":0.21999999999999886,"changePct":1.3888888888888817,"marketStatus":"OPEN"}],"vix":{"name":"VIX","symbol":"^VIX","currency":"USD","price":16.06,"change":0.21999999999999886,"changePct":1.3888888888888817,"marketStatus":"OPEN"},"mood":{"score":70,"label":"탐욕","tone":"greed","summary":"코스닥 강세(5.47%) · VIX 안정(16.1) → 위험선호(리스크온) 심리"},"forex":[{"name":"원/달러","symbol":"KRW=X","price":1505.13,"change":-1.35,"changePct":-0.08961287239126368},{"name":"원/100엔","symbol":"JPYKRW=X","price":928.8,"change":3.4,"changePct":0.36740868813487043}],"briefs":[{"key":"KOSPI","name":"코스피","changePct":2.52,"price":7475.94,"flow":{"date":"20260710","personal":-7805,"foreign":-3228,"institution":11314},"reason":{"dir":"up","query":"코스피 급등 이유","headlines":[],"ai":null,"sig":"3|코스피 2.5% 상승해 7,400대…코스닥 급등|[속보] 코스피 2.5% 상승해 7,400대…코스닥 5.4% 급등|코스피 5%대 급등, 매수 사이드카 발동…올 들어 벌써 34번째 [투자360]|[속보]코스피 급등에 매수 사이드카 발동"}},{"key":"KOSDAQ","name":"코스닥","changePct":5.47,"price":837.43,"flow":{"date":"20260710","personal":-4213,"foreign":-1563,"institution":5825},"reason":{"dir":"up","query":"코스닥 급등 이유","headlines":[],"ai":null,"sig":"5|코스피 2.5% 상승해 7,400대…코스닥 급등|코스피 2.5% 상승해 7400대 마감…코스닥 5.4% 급등|[마감시황] 코스닥 837.43 마감…기관 5825억원 순매수에 5.47% 급등|코스피 2.5% 상승해 7,400선 장 마감…코스닥 5.4% 급등"}}]}